modeanalytics/__init__.py
modeanalytics/admin.py
modeanalytics/apps.py
modeanalytics/models.py
modeanalytics/tests.py
modeanalytics/views.py
modeanalytics/migrations/0001_initial.py
modeanalytics/migrations/0002_auto_20200317_2144.py
modeanalytics/migrations/0003_auto_20200319_0226.py
modeanalytics/migrations/0004_remove_modereportmodel_space.py
modeanalytics/migrations/__init__.py
test_app/migrations/0001_initial.py
test_app/migrations/__init__.py
modeanalytics-0.1.3.dist-info/LICENSE
modeanalytics-0.1.3.dist-info/METADATA
modeanalytics-0.1.3.dist-info/WHEEL
modeanalytics-0.1.3.dist-info/top_level.txt
modeanalytics-0.1.3.dist-info/RECORD
